[
  {
    "id": "0",
    "title": "「子供が幸せな国」日本は14番",
    "source": "https://www3.nhk.or.jp/news/easy/ne2025051512144/ne2025051512144.html",
    "article_html": "「子供が幸せかどうか」について、ユニセフが調べました。<br/>日本は、OECDやEUなど36の国の中で14番でした。5年前の20番より上がりました。<br/>「体の健康」「勉強などの能力」「心の健康」の3つについて調べました。<br/>太りすぎている割合や子どものときに亡くなる割合など「体の健康」は1番でした。<br/>「勉強などの能力」は5年前より上がって12番でした。<br/>「心の健康」は5年前より上がりましたが、32番でした。日本は子どもが自殺する割合が増えています。<br/>ユニセフは、親と子どもがいい関係になるための支援や、暴力やいじめなどをなくすことが必要だと言っています。",
    "tags": [],

    "grammarPointsUsed": ["について", "など", "より", "すぎる", "と言いう"],
    "questions": [
      "1. 5年前に、日本は何番でしたか？",
      "2. 今に、日本は何番ですか？",
      "3. ユニセフは、何が必要と言いましたか？"
    ],
    "answers": [
      "1. 20番",
      "2. 14番",
      "3. 暴力やいじめなどをなくすことが必要だ。"
    ]
  }
]
